fletora/__init__.py
fletora/app.py
fletora/html.py
fletora/plugins.py
fletora-0.0.3.dist-info/METADATA
fletora-0.0.3.dist-info/WHEEL
fletora-0.0.3.dist-info/top_level.txt
fletora-0.0.3.dist-info/RECORD
