Metadata-Version: 2.2
Name: fletora
Version: 0.0.3
Summary: Add your description here
License: MIT License
Requires-Python: >=3.13
Requires-Dist: arel>=0.3.0
Requires-Dist: fastapi[standard]>=0.115.8
